[
  {
    "ts": "2025-11-05T09:04:42Z",
    "sourceCurrency": "GBP",
    "targetCurrency": "USD",
    "sourceAmount": 10,
    "rate": 1.30495,
    "payIn": "BALANCE",
    "payOut": "BALANCE",
    "targetAmount": 13.01,
    "fee_total": 0.03,
    "status": "ok",
    "mode": "BALANCE",
    "src": "GBP",
    "tgt": "USD",
    "amount": 10,
    "midTarget": 13.0495,
    "fee_bps": 30.2693589792713,
    "bps": 30.2693589792713,
    "bps_vs_mid": 30.2693589792713,
    "y": 30.2693589792713,
    "x": 10,
    "pair": "GBP->USD"
  },
  {
    "ts": "2025-11-05T09:04:42Z",
    "sourceCurrency": "GBP",
    "targetCurrency": "USD",
    "sourceAmount": 100,
    "rate": 1.30495,
    "payIn": "BALANCE",
    "payOut": "BALANCE",
    "targetAmount": 130.03,
    "fee_total": 0.36,
    "status": "ok",
    "mode": "BALANCE",
    "src": "GBP",
    "tgt": "USD",
    "amount": 100,
    "midTarget": 130.495,
    "fee_bps": 35.63354917813011,
    "bps": 35.63354917813011,
    "bps_vs_mid": 35.63354917813011,
    "y": 35.63354917813011,
    "x": 100,
    "pair": "GBP->USD"
  },
  {
    "ts": "2025-11-05T09:04:42Z",
    "sourceCurrency": "GBP",
    "targetCurrency": "USD",
    "sourceAmount": 1000,
    "rate": 1.30495,
    "payIn": "BALANCE",
    "payOut": "BALANCE",
    "targetAmount": 1300.27,
    "fee_total": 3.59,
    "status": "ok",
    "mode": "BALANCE",
    "src": "GBP",
    "tgt": "USD",
    "amount": 1000,
    "midTarget": 1304.95,
    "fee_bps": 35.86344304379541,
    "bps": 35.86344304379541,
    "bps_vs_mid": 35.86344304379541,
    "y": 35.86344304379541,
    "x": 1000,
    "pair": "GBP->USD"
  },
  {
    "ts": "2025-11-05T09:04:42Z",
    "sourceCurrency": "GBP",
    "targetCurrency": "USD",
    "sourceAmount": 10000,
    "rate": 1.30495,
    "payIn": "BALANCE",
    "payOut": "BALANCE",
    "targetAmount": 13002.69,
    "fee_total": 35.87,
    "status": "ok",
    "mode": "BALANCE",
    "src": "GBP",
    "tgt": "USD",
    "amount": 10000,
    "midTarget": 13049.5,
    "fee_bps": 35.871106172650215,
    "bps": 35.871106172650215,
    "bps_vs_mid": 35.871106172650215,
    "y": 35.871106172650215,
    "x": 10000,
    "pair": "GBP->USD"
  },
  {
    "ts": "2025-11-05T09:04:42Z",
    "sourceCurrency": "GBP",
    "targetCurrency": "USD",
    "sourceAmount": 100000,
    "rate": 1.30495,
    "payIn": "BALANCE",
    "payOut": "BALANCE",
    "targetAmount": 130131.74,
    "fee_total": 278.37,
    "status": "ok",
    "mode": "BALANCE",
    "src": "GBP",
    "tgt": "USD",
    "amount": 100000,
    "midTarget": 130495,
    "fee_bps": 27.837081880531798,
    "bps": 27.837081880531798,
    "bps_vs_mid": 27.837081880531798,
    "y": 27.837081880531798,
    "x": 100000,
    "pair": "GBP->USD"
  },
  {
    "ts": "2025-11-05T09:04:42Z",
    "sourceCurrency": "GBP",
    "targetCurrency": "USD",
    "sourceAmount": 1000000,
    "rate": 1.30495,
    "payIn": "BALANCE",
    "payOut": "BALANCE",
    "targetAmount": 1302077.07,
    "fee_total": 2201.56,
    "status": "ok",
    "mode": "BALANCE",
    "src": "GBP",
    "tgt": "USD",
    "amount": 1000000,
    "midTarget": 1304950,
    "fee_bps": 22.01563278286467,
    "bps": 22.01563278286467,
    "bps_vs_mid": 22.01563278286467,
    "y": 22.01563278286467,
    "x": 1000000,
    "pair": "GBP->USD"
  },
  {
    "ts": "2025-11-05T09:04:42Z",
    "sourceCurrency": "USD",
    "targetCurrency": "JPY",
    "sourceAmount": 10,
    "rate": 153.525,
    "payIn": "BALANCE",
    "payOut": "BALANCE",
    "targetAmount": 1531,
    "fee_total": 0.03,
    "status": "ok",
    "mode": "BALANCE",
    "src": "USD",
    "tgt": "JPY",
    "amount": 10,
    "midTarget": 1535.25,
    "fee_bps": 27.682787819572894,
    "bps": 27.682787819572894,
    "bps_vs_mid": 27.682787819572894,
    "y": 27.682787819572894,
    "x": 10,
    "pair": "USD->JPY"
  },
  {
    "ts": "2025-11-05T09:04:42Z",
    "sourceCurrency": "USD",
    "targetCurrency": "JPY",
    "sourceAmount": 100,
    "rate": 153.525,
    "payIn": "BALANCE",
    "payOut": "BALANCE",
    "targetAmount": 15297,
    "fee_total": 0.36,
    "status": "ok",
    "mode": "BALANCE",
    "src": "USD",
    "tgt": "JPY",
    "amount": 100,
    "midTarget": 15352.5,
    "fee_bps": 36.15046409379596,
    "bps": 36.15046409379596,
    "bps_vs_mid": 36.15046409379596,
    "y": 36.15046409379596,
    "x": 100,
    "pair": "USD->JPY"
  },
  {
    "ts": "2025-11-05T09:04:42Z",
    "sourceCurrency": "USD",
    "targetCurrency": "JPY",
    "sourceAmount": 1000,
    "rate": 153.525,
    "payIn": "BALANCE",
    "payOut": "BALANCE",
    "targetAmount": 152974,
    "fee_total": 3.59,
    "status": "ok",
    "mode": "BALANCE",
    "src": "USD",
    "tgt": "JPY",
    "amount": 1000,
    "midTarget": 153525,
    "fee_bps": 35.889920208435065,
    "bps": 35.889920208435065,
    "bps_vs_mid": 35.889920208435065,
    "y": 35.889920208435065,
    "x": 1000,
    "pair": "USD->JPY"
  },
  {
    "ts": "2025-11-05T09:04:42Z",
    "sourceCurrency": "USD",
    "targetCurrency": "JPY",
    "sourceAmount": 10000,
    "rate": 153.525,
    "payIn": "BALANCE",
    "payOut": "BALANCE",
    "targetAmount": 1529743,
    "fee_total": 35.87,
    "status": "ok",
    "mode": "BALANCE",
    "src": "USD",
    "tgt": "JPY",
    "amount": 10000,
    "midTarget": 1535250,
    "fee_bps": 35.87037941703342,
    "bps": 35.87037941703342,
    "bps_vs_mid": 35.87037941703342,
    "y": 35.87037941703342,
    "x": 10000,
    "pair": "USD->JPY"
  },
  {
    "ts": "2025-11-05T09:04:42Z",
    "sourceCurrency": "USD",
    "targetCurrency": "JPY",
    "sourceAmount": 100000,
    "rate": 153.525,
    "payIn": "BALANCE",
    "payOut": "BALANCE",
    "targetAmount": 15308873,
    "fee_total": 284.17,
    "status": "ok",
    "mode": "BALANCE",
    "src": "USD",
    "tgt": "JPY",
    "amount": 100000,
    "midTarget": 15352500,
    "fee_bps": 28.416870216576573,
    "bps": 28.416870216576573,
    "bps_vs_mid": 28.416870216576573,
    "y": 28.416870216576573,
    "x": 100000,
    "pair": "USD->JPY"
  },
  {
    "ts": "2025-11-05T09:04:42Z",
    "sourceCurrency": "USD",
    "targetCurrency": "JPY",
    "sourceAmount": 1000000,
    "rate": 153.525,
    "payIn": "BALANCE",
    "payOut": "BALANCE",
    "targetAmount": 153176535,
    "fee_total": 2269.76,
    "status": "ok",
    "mode": "BALANCE",
    "src": "USD",
    "tgt": "JPY",
    "amount": 1000000,
    "midTarget": 153525000,
    "fee_bps": 22.697606253053728,
    "bps": 22.697606253053728,
    "bps_vs_mid": 22.697606253053728,
    "y": 22.697606253053728,
    "x": 1000000,
    "pair": "USD->JPY"
  },
  {
    "ts": "2025-11-05T09:04:42Z",
    "sourceCurrency": "SGD",
    "targetCurrency": "USD",
    "sourceAmount": 10,
    "rate": 0.765638,
    "payIn": "BALANCE",
    "payOut": "BALANCE",
    "targetAmount": 7.64,
    "fee_total": 0.02,
    "status": "ok",
    "mode": "BALANCE",
    "src": "SGD",
    "tgt": "USD",
    "amount": 10,
    "midTarget": 7.65638,
    "fee_bps": 21.393922454215897,
    "bps": 21.393922454215897,
    "bps_vs_mid": 21.393922454215897,
    "y": 21.393922454215897,
    "x": 10,
    "pair": "SGD->USD"
  },
  {
    "ts": "2025-11-05T09:04:42Z",
    "sourceCurrency": "SGD",
    "targetCurrency": "USD",
    "sourceAmount": 100,
    "rate": 0.765638,
    "payIn": "BALANCE",
    "payOut": "BALANCE",
    "targetAmount": 76.36,
    "fee_total": 0.26,
    "status": "ok",
    "mode": "BALANCE",
    "src": "SGD",
    "tgt": "USD",
    "amount": 100,
    "midTarget": 76.5638,
    "fee_bps": 26.618323541934828,
    "bps": 26.618323541934828,
    "bps_vs_mid": 26.618323541934828,
    "y": 26.618323541934828,
    "x": 100,
    "pair": "SGD->USD"
  },
  {
    "ts": "2025-11-05T09:04:42Z",
    "sourceCurrency": "SGD",
    "targetCurrency": "USD",
    "sourceAmount": 1000,
    "rate": 0.765638,
    "payIn": "BALANCE",
    "payOut": "BALANCE",
    "targetAmount": 763.65,
    "fee_total": 2.6,
    "status": "ok",
    "mode": "BALANCE",
    "src": "SGD",
    "tgt": "USD",
    "amount": 1000,
    "midTarget": 765.638,
    "fee_bps": 25.96527340597121,
    "bps": 25.96527340597121,
    "bps_vs_mid": 25.96527340597121,
    "y": 25.96527340597121,
    "x": 1000,
    "pair": "SGD->USD"
  },
  {
    "ts": "2025-11-05T09:04:42Z",
    "sourceCurrency": "SGD",
    "targetCurrency": "USD",
    "sourceAmount": 10000,
    "rate": 0.765638,
    "payIn": "BALANCE",
    "payOut": "BALANCE",
    "targetAmount": 7636.52,
    "fee_total": 25.94,
    "status": "ok",
    "mode": "BALANCE",
    "src": "SGD",
    "tgt": "USD",
    "amount": 10000,
    "midTarget": 7656.38,
    "fee_bps": 25.93915140053138,
    "bps": 25.93915140053138,
    "bps_vs_mid": 25.93915140053138,
    "y": 25.93915140053138,
    "x": 10000,
    "pair": "SGD->USD"
  },
  {
    "ts": "2025-11-05T09:04:42Z",
    "sourceCurrency": "SGD",
    "targetCurrency": "USD",
    "sourceAmount": 100000,
    "rate": 0.765638,
    "payIn": "BALANCE",
    "payOut": "BALANCE",
    "targetAmount": 76416.57,
    "fee_total": 192.3,
    "status": "ok",
    "mode": "BALANCE",
    "src": "SGD",
    "tgt": "USD",
    "amount": 100000,
    "midTarget": 76563.8,
    "fee_bps": 19.229714303625745,
    "bps": 19.229714303625745,
    "bps_vs_mid": 19.229714303625745,
    "y": 19.229714303625745,
    "x": 100000,
    "pair": "SGD->USD"
  },
  {
    "ts": "2025-11-05T09:04:42Z",
    "sourceCurrency": "SGD",
    "targetCurrency": "USD",
    "sourceAmount": 1000000,
    "rate": 0.765638,
    "payIn": "BALANCE",
    "payOut": "BALANCE",
    "targetAmount": 764598.66,
    "fee_total": 1357.48,
    "status": "ok",
    "mode": "BALANCE",
    "src": "SGD",
    "tgt": "USD",
    "amount": 1000000,
    "midTarget": 765638,
    "fee_bps": 13.574822566277955,
    "bps": 13.574822566277955,
    "bps_vs_mid": 13.574822566277955,
    "y": 13.574822566277955,
    "x": 1000000,
    "pair": "SGD->USD"
  },
  {
    "ts": "2025-11-05T09:04:42Z",
    "sourceCurrency": "EUR",
    "targetCurrency": "USD",
    "sourceAmount": 10,
    "rate": 1.1489,
    "payIn": "BALANCE",
    "payOut": "BALANCE",
    "targetAmount": 11.44,
    "fee_total": 0.04,
    "status": "ok",
    "mode": "BALANCE",
    "src": "EUR",
    "tgt": "USD",
    "amount": 10,
    "midTarget": 11.489,
    "fee_bps": 42.64949081730474,
    "bps": 42.64949081730474,
    "bps_vs_mid": 42.64949081730474,
    "y": 42.64949081730474,
    "x": 10,
    "pair": "EUR->USD"
  },
  {
    "ts": "2025-11-05T09:04:42Z",
    "sourceCurrency": "EUR",
    "targetCurrency": "USD",
    "sourceAmount": 100,
    "rate": 1.1489,
    "payIn": "BALANCE",
    "payOut": "BALANCE",
    "targetAmount": 114.35,
    "fee_total": 0.47,
    "status": "ok",
    "mode": "BALANCE",
    "src": "EUR",
    "tgt": "USD",
    "amount": 100,
    "midTarget": 114.89,
    "fee_bps": 47.001479676213044,
    "bps": 47.001479676213044,
    "bps_vs_mid": 47.001479676213044,
    "y": 47.001479676213044,
    "x": 100,
    "pair": "EUR->USD"
  },
  {
    "ts": "2025-11-05T09:04:42Z",
    "sourceCurrency": "EUR",
    "targetCurrency": "USD",
    "sourceAmount": 1000,
    "rate": 1.1489,
    "payIn": "BALANCE",
    "payOut": "BALANCE",
    "targetAmount": 1143.52,
    "fee_total": 4.68,
    "status": "ok",
    "mode": "BALANCE",
    "src": "EUR",
    "tgt": "USD",
    "amount": 1000,
    "midTarget": 1148.9,
    "fee_bps": 46.82740012185715,
    "bps": 46.82740012185715,
    "bps_vs_mid": 46.82740012185715,
    "y": 46.82740012185715,
    "x": 1000,
    "pair": "EUR->USD"
  },
  {
    "ts": "2025-11-05T09:04:42Z",
    "sourceCurrency": "EUR",
    "targetCurrency": "USD",
    "sourceAmount": 10000,
    "rate": 1.1489,
    "payIn": "BALANCE",
    "payOut": "BALANCE",
    "targetAmount": 11435.24,
    "fee_total": 46.79,
    "status": "ok",
    "mode": "BALANCE",
    "src": "EUR",
    "tgt": "USD",
    "amount": 10000,
    "midTarget": 11489,
    "fee_bps": 46.79258421098509,
    "bps": 46.79258421098509,
    "bps_vs_mid": 46.79258421098509,
    "y": 46.79258421098509,
    "x": 10000,
    "pair": "EUR->USD"
  },
  {
    "ts": "2025-11-05T09:04:42Z",
    "sourceCurrency": "EUR",
    "targetCurrency": "USD",
    "sourceAmount": 100000,
    "rate": 1.1489,
    "payIn": "BALANCE",
    "payOut": "BALANCE",
    "targetAmount": 114441.66,
    "fee_total": 390.23,
    "status": "ok",
    "mode": "BALANCE",
    "src": "EUR",
    "tgt": "USD",
    "amount": 100000,
    "midTarget": 114890,
    "fee_bps": 39.02341370006113,
    "bps": 39.02341370006113,
    "bps_vs_mid": 39.02341370006113,
    "y": 39.02341370006113,
    "x": 100000,
    "pair": "EUR->USD"
  },
  {
    "ts": "2025-11-05T09:04:42Z",
    "sourceCurrency": "EUR",
    "targetCurrency": "USD",
    "sourceAmount": 1000000,
    "rate": 1.1489,
    "payIn": "BALANCE",
    "payOut": "BALANCE",
    "targetAmount": 1145076.30,
    "fee_total": 3328.14,
    "status": "ok",
    "mode": "BALANCE",
    "src": "EUR",
    "tgt": "USD",
    "amount": 1000000,
    "midTarget": 1148900,
    "fee_bps": 33.28139959961618,
    "bps": 33.28139959961618,
    "bps_vs_mid": 33.28139959961618,
    "y": 33.28139959961618,
    "x": 1000000,
    "pair": "EUR->USD"
  }
]
